LICENSE
README.md
setup.py
model_f5_tts/__init__.py
ttslab/__init__.py
ttslab.egg-info/PKG-INFO
ttslab.egg-info/SOURCES.txt
ttslab.egg-info/dependency_links.txt
ttslab.egg-info/entry_points.txt
ttslab.egg-info/requires.txt
ttslab.egg-info/top_level.txt
ttslab/cli/__init__.py
ttslab/cli/install.py
ttslab/cli/list.py
ttslab/cli/prune.py
ttslab/cli/serve.py
ttslab/cli/uninstall.py
ttslab/utils/__init__.py
ttslab/utils/environment.py
ttslab/utils/storage.py
ttslab/web/__init__.py