Metadata-Version: 2.1
Name: ttslab
Version: 0.1.0
Summary: Run TTS models.
Classifier: License :: OSI Approved :: BSD License
Classifier: Programming Language :: Python :: 3
License-File: LICENSE
Requires-Dist: click
Requires-Dist: rich
Requires-Dist: flask
Requires-Dist: gitpython
Requires-Dist: uv
